{
  "type": "root",
  "children": [
    {
      "type": "doctype",
      "value": "html"
    },
    {
      "type": "element",
      "tag": "html",
      "properties": {
        "lang": "en"
      },
      "openclose": false,
      "children": [
        {
          "type": "element",
          "tag": "head",
          "properties": {},
          "openclose": false,
          "children": [
            {
              "type": "element",
              "tag": "meta",
              "properties": {
                "charset": "UTF-8"
              },
              "openclose": true,
              "children": [],
              "locals": {}
            },
            {
              "type": "element",
              "tag": "meta",
              "properties": {
                "http-equiv": "X-UA-Compatible",
                "content": "IE=edge"
              },
              "openclose": true,
              "children": [],
              "locals": {}
            },
            {
              "type": "element",
              "tag": "meta",
              "properties": {
                "name": "viewport",
                "content": "width=device-width, initial-scale=1.0"
              },
              "openclose": true,
              "children": [],
              "locals": {}
            },
            {
              "type": "element",
              "tag": "title",
              "properties": {},
              "openclose": false,
              "children": [
                {
                  "type": "text",
                  "value": "Document"
                }
              ],
              "locals": {}
            }
          ],
          "locals": {}
        },
        {
          "type": "element",
          "tag": "body",
          "properties": {},
          "openclose": false,
          "children": [
            {
              "type": "comment",
              "value": " Test Comment "
            },
            {
              "type": "element",
              "tag": "h1",
              "properties": {},
              "openclose": false,
              "children": [
                {
                  "type": "text",
                  "value": "Hello World!"
                }
              ],
              "locals": {}
            }
          ],
          "locals": {}
        }
      ],
      "locals": {}
    }
  ]
}